trawsate/__init__.py
trawsate/__main__.py
trawsate/parallel.py
trawsate/promise.py
trawsate/rotator.py
trawsate/single.py
trawsate/travis.py
trawsate-0.0.1.dist-info/DESCRIPTION.rst
trawsate-0.0.1.dist-info/METADATA
trawsate-0.0.1.dist-info/RECORD
trawsate-0.0.1.dist-info/WHEEL
trawsate-0.0.1.dist-info/entry_points.txt
trawsate-0.0.1.dist-info/metadata.json
trawsate-0.0.1.dist-info/top_level.txt
trawsate-0.0.1.dist-info/zip-safe
